<?xml version="1.0" encoding="UTF-8" standalone="no"?><?Xpress productLine="ncc-clause" ?><clause id="_e6778821-4f0d-49dc-8a59-df695f8f4cee" outputclass="ncc-clause" variation="NT"><meta><facet building="Class 2"/><facet building="Class 3"/><facet building="Class 4"/><facet building="Class 5"/><facet building="Class 6"/><facet building="Class 7a"/><facet building="Class 7b"/><facet building="Class 8"/><facet building="Class 9a"/><facet building="Class 9b"/><facet building="Class 9c"/><facet building="Class 10b"/><facet building="Class 10c"/></meta><sptc>10.7.2</sptc><title id="_d018c097-545f-467d-bef8-3c5514616144">General installation requirements for walls</title><archive-num>2019: NT 3.8.6.3</archive-num><subclause id="_224460e9-f14b-41ec-99a9-9b2ef2bd5612" outputclass="subclause"><title id="_5c209ec6-18ea-4ce1-b358-4d51e9b5f866">SubClause</title><num>1</num><p>To achieve an appropriate R<sub id="_8fdf5ac6-3bae-4394-9525-5dec62e2597b">W</sub> and impact sound resistance, walls must—</p><ol outputclass="alpha"><li id="_b4f36565-2525-41b6-9c27-94724b40d1d3">be installed in accordance with the appropriate requirements contained in (2) to (6); and</li><li id="_f30e0adc-86af-4e0d-a9db-842ae1760e52">at the junction of sound insulated walls with perimeter walls and roof cladding, be sealed in accordance with any details in <xref format="dita" href="/tmp/QppServer/Publishing/5e2c1f63-e589-4ce1-95e8-5c3e286a7aff/7049_0.5.0.xml#_6a6b1efe-3d59-4443-a7c1-ca2ed88e56f5" id="_385112f3-c983-4ae6-97aa-01665c9bce7c" referencetype="Text" scope="local" synctargettext="false" type="image-reference">Figure NT 10.7.2a</xref>.</li></ol></subclause><subclause id="_c7536d6d-ed25-4753-b70c-eb0b9167429d" outputclass="subclause"><title id="_90bb1947-0ce4-4ecd-baa5-1ac927b77e70">SubClause</title><num>2</num><p>Masonry units must—</p><ol outputclass="alpha"><li id="_cff0c91c-bd9a-4801-91f8-eb7d3bf6ad2e">be laid with all joints filled solid, including those between the masonry and any adjoining construction; and</li><li id="_94ea4c94-c254-4aeb-927e-3bd8983f5f8b">not be chased for services.</li></ol></subclause><subclause id="_add6c657-b4f0-4acd-9551-4d27d9c57cf4" outputclass="subclause"><title id="_dd38f29c-6e03-4aea-81bc-828578e28973">SubClause</title><num>3</num><p>Joints between concrete slabs and any adjoining construction must be filed solid.</p></subclause><subclause id="_7578b2d9-eb2d-4e2e-b31c-63fb8dcee2e2" outputclass="subclause"><title id="_171ae0f4-87fe-4952-b0bd-c009c45e19a1">SubClause</title><num>4</num><p>Plasterboard must be installed as follows:</p><ol outputclass="alpha"><li id="_2d5b892e-a46d-45fc-9c7f-e55ad9e82933">If one layer is <xref format="dita" href="/tmp/QppServer/Publishing/5e2c1f63-e589-4ce1-95e8-5c3e286a7aff/1432_4.0.0.xml#_af6fde9f-147d-4782-8b85-42044e80fd42" id="_4635a1d8-9d2c-42f8-b68b-5de7f3dee5b3" referencetype="Text" scope="local" synctargettext="false" type="abcb-glossentry">required</xref> under this Part, joints must be staggered with the joints in sheets on the opposite face of the wall.</li><li id="_f1c3b990-81b3-4486-acbe-8c6473675f18">If 2 layers are <xref format="dita" href="/tmp/QppServer/Publishing/5e2c1f63-e589-4ce1-95e8-5c3e286a7aff/1432_4.0.0.xml#_af6fde9f-147d-4782-8b85-42044e80fd42" id="_d477b187-779c-446c-9138-144a290d473a" referencetype="Text" scope="local" synctargettext="false" type="abcb-glossentry">required</xref>, the first layer must be fixed according to (a) and the second layer must be fixed to the first layer with nails, screws or adhesive so that the joints do not coincide with those of the first layer (see <xref format="dita" href="/tmp/QppServer/Publishing/5e2c1f63-e589-4ce1-95e8-5c3e286a7aff/7050_0.5.0.xml#_1908c5d3-a7b5-4628-9858-682852cd46b7" id="_1bf75018-0c26-4ff4-ad21-a3153c768c8b" referencetype="Text" scope="local" synctargettext="false" type="image-reference">Figure NT 10.7.2b</xref>).</li><li id="_0ec86806-6d8f-4e4c-9abb-7da1c13aadfa">Joints between sheets or between sheets and any adjoining construction must be taped and filled solid.</li><li id="_ea45d050-390a-466d-a383-710db9fecc81">Fire-protective grade plasterboard (where nominated) must be the grade manufactured for use in fire-resisting construction.</li></ol></subclause><subclause id="_88abec78-9ab8-4f10-9ed3-f5ef48cbe122" outputclass="subclause"><title id="_4f5feffa-f1a1-41b0-9d62-091a044fbf39">SubClause</title><num>5</num><p>Steel studs and perimeter members must be installed as follows:</p><ol outputclass="alpha"><li id="_c120befc-9a1b-4723-9a19-3311cde5fd32">The section of steel must be not less than 0.6 mm thick.</li><li id="_aa7f1589-8f2b-4612-beb5-f471b1d62814">Studs must be not less than 63 mm in depth unless another depth is specified in <xref format="dita" href="/tmp/QppServer/Publishing/5e2c1f63-e589-4ce1-95e8-5c3e286a7aff/7025_0.16.0.xml#_bf743386-3496-4df4-999d-6259a2661f18" id="_1d819ab0-7c2c-4c46-a471-e5882d5cdb4c" referencetype="Text" scope="local" synctargettext="false" type="ncc-clause">NT 10.7.1</xref>.</li><li id="_200a431b-7bea-4125-9320-6e18760eacc9">Studs must be fixed to steel top and bottom plates of sufficient depth to permit secure fixing of the plasterboard.</li><li id="_8e12c958-f326-4247-8762-e6d8f19516fd">All steel members at the perimeter of the wall must be securely fixed to the adjoining structure and be bedded in resilient compound or the joints must be caulked so that there are no voids between the steel members and the wall.</li></ol></subclause><subclause id="_aa38f549-88bc-40bd-aa16-0d08d9911884" outputclass="subclause"><title id="_3841528c-2954-4026-92e8-5e1ea55d9d03">SubClause</title><num>6</num><p>Timber studs and permitter members must be installed as follows:</p><ol outputclass="alpha"><li id="_3ed4a9c5-6cc4-4c56-af54-4a7f8ea52099">Studs must be fixed to top and bottom plates of sufficient depth to permit secure fixing of the plasterboard.</li><li id="_e55e44aa-0df3-426e-8702-ec8f3802b192">Noggings and like members must not bridge between studs supporting different wall leaves.</li><li id="_c1ba6f5d-4344-47c4-99d3-b24306d429ea">All timber members at the perimeter of the wall must be securely fixed to the adjoining structure and bedded in resilient compound or the joints must be caulked so that there are no voids between the timber members and the wall.</li></ol></subclause><image-reference conref="/tmp/QppServer/Publishing/5e2c1f63-e589-4ce1-95e8-5c3e286a7aff/7049_0.5.0.xml" id="_6a6b1efe-3d59-4443-a7c1-ca2ed88e56f5" variation="NT"><num/><title id="_bb35c692-15bf-421c-8120-405156cf2797"/></image-reference><image-reference conref="/tmp/QppServer/Publishing/5e2c1f63-e589-4ce1-95e8-5c3e286a7aff/7050_0.5.0.xml" id="_1908c5d3-a7b5-4628-9858-682852cd46b7" variation="NT"><num/><title id="_80216243-2467-4ef9-9d05-dbadd9475d14"/></image-reference></clause>