<?xml version="1.0" encoding="UTF-8" standalone="no"?><?Xpress productLine="standard-part" ?><part xmlns:qxa="true" xmlns:xt="urn:xpressauthor:trackchanges" id="_0d4a5c73-9436-4335-a09a-c15c837d51b2" outputclass="standard-part"><num>10.8</num><title id="_fda55b0b-b137-40b9-8877-65db26383573">Condensation management</title><clauseref id="_283f52c2-1d53-4039-99ac-2fa034a8b4ca" outputclass="clausref-national"><clause conref="/tmp/QppServer/Publishing/5e2c1f63-e589-4ce1-95e8-5c3e286a7aff/2037_1.47.0.xml" id="_3ed213c2-0a0f-410f-8cbf-b06a4a459f42" outputclass="ncc-clause"><meta xmlns:inv="urn:xpressauthor:xpressdocument" inv:access="external"><facet building="Class 2" inv:access="external"/><facet building="Class 3" inv:access="external"/><facet building="Class 4" inv:access="external"/><facet building="Class 5" inv:access="external"/><facet building="Class 6" inv:access="external"/><facet building="Class 7a" inv:access="external"/><facet building="Class 7b" inv:access="external"/><facet building="Class 8" inv:access="external"/><facet building="Class 9a" inv:access="external"/><facet building="Class 9b" inv:access="external"/><facet building="Class 9c" inv:access="external"/><facet building="Class 10b" inv:access="external"/><facet building="Class 10c" inv:access="external"/></meta><sptc/><title id="_b1e43914-9a7c-435b-a359-73353b3ed948"/><archive-num/></clause></clauseref><clauseref id="_08060d1c-6121-41b4-a464-c05aa51f08b5" outputclass="clausref-national"><clause conref="/tmp/QppServer/Publishing/5e2c1f63-e589-4ce1-95e8-5c3e286a7aff/2038_1.19.0.xml" id="_5c59fc38-f94f-4b8e-a344-d714a24c0704" outputclass="ncc-clause"><meta xmlns:inv="urn:xpressauthor:xpressdocument" inv:access="external"><facet building="Class 2" inv:access="external"/><facet building="Class 3" inv:access="external"/><facet building="Class 4" inv:access="external"/><facet building="Class 5" inv:access="external"/><facet building="Class 6" inv:access="external"/><facet building="Class 7a" inv:access="external"/><facet building="Class 7b" inv:access="external"/><facet building="Class 8" inv:access="external"/><facet building="Class 9a" inv:access="external"/><facet building="Class 9b" inv:access="external"/><facet building="Class 9c" inv:access="external"/><facet building="Class 10b" inv:access="external"/><facet building="Class 10c" inv:access="external"/></meta><sptc/><title id="_35a217d8-9575-49ec-921b-8c717ca439a5"/><archive-num/></clause></clauseref><clauseref id="_49cf6fd0-fe74-4e43-a6a9-97c49e300875" outputclass="clausref-national"><clause conref="/tmp/QppServer/Publishing/5e2c1f63-e589-4ce1-95e8-5c3e286a7aff/2039_1.43.0.xml" id="_c4feece9-e6aa-4e96-84b1-751f352f799a" outputclass="ncc-clause"><meta xmlns:inv="urn:xpressauthor:xpressdocument" inv:access="external"><facet building="Class 2" inv:access="external"/><facet building="Class 3" inv:access="external"/><facet building="Class 4" inv:access="external"/><facet building="Class 5" inv:access="external"/><facet building="Class 6" inv:access="external"/><facet building="Class 7a" inv:access="external"/><facet building="Class 7b" inv:access="external"/><facet building="Class 8" inv:access="external"/><facet building="Class 9a" inv:access="external"/><facet building="Class 9b" inv:access="external"/><facet building="Class 9c" inv:access="external"/><facet building="Class 10b" inv:access="external"/><facet building="Class 10c" inv:access="external"/><facet climate="Climate zone 1" inv:access="external"/><facet climate="Climate zone 2" inv:access="external"/><facet climate="Climate zone 3" inv:access="external"/><facet climate="Climate zone 4" inv:access="external"/><facet climate="Climate zone 5" inv:access="external"/></meta><sptc/><title id="_1df4e78b-5dd6-4ca4-a28d-cb54999b5058"/><archive-num/></clause></clauseref><clauseref id="_00aa76f7-9853-4160-bacd-ca5c2740db5d" outputclass="clausref-national" xt:author="Jerome Samuel" xt:dateTime="2024-02-27T09:42:39" xt:type="insert"><clause conref="/tmp/QppServer/Publishing/5e2c1f63-e589-4ce1-95e8-5c3e286a7aff/9320_0.21.0.xml" id="_ab69a8f2-99a3-4d74-9a9f-c65f13687a28" outputclass="ncc-clause" xt:author="Jerome Samuel" xt:dateTime="2024-02-27T09:43:49" xt:type="insert"><sptc xt:author="Jerome Samuel" xt:dateTime="2024-02-27T09:43:49" xt:type="insert"/><title id="_4cf8117a-e5c6-4947-ab4f-c56dc77139ec" xt:author="Jerome Samuel" xt:dateTime="2024-02-27T09:43:49" xt:type="insert"/><archive-num xt:author="Jerome Samuel" xt:dateTime="2024-02-27T09:43:49" xt:type="insert"/></clause></clauseref></part>