<?xml version="1.0" encoding="UTF-8" standalone="no"?><?Xpress productLine="abcb-glossentry" ?><abcb-glossentry id="_98f99be0-5c03-48a8-8087-27bc99acc90d" outputclass="abcb-glossentry"><glossterm id="_5bf7146f-9992-4e0e-93ec-30e31bdb3566">Open-deck carpark</glossterm><glossdef outputclass="glossdef"><p>A carpark in which all parts of the parking <xref format="dita" href="/tmp/QppServer/Publishing/5e2c1f63-e589-4ce1-95e8-5c3e286a7aff/1483_25.0.0.xml#_53ff3ea1-55e7-4f2a-b2b3-ca445ff64c15" id="_0bf86028-2485-4e43-bfd0-3ad3f79f9b01" scope="local" type="abcb-glossentry">storeys</xref> are cross-ventilated by permanent unobstructed openings in not fewer than 2 opposite or approximately opposite sides, and—</p><ol outputclass="alpha"><li>each side that provides ventilation is not less than <sup id="_78e1683b-d24b-45cb-aacf-2d379c355e3a">1</sup>/<sub id="_f3a62cc1-5747-4bd5-96a3-0413ff657638">6 </sub>of the area of any other side; and</li><li>the openings are not less than ½ of the wall area of the side concerned.</li></ol></glossdef></abcb-glossentry>