<?xml version="1.0" encoding="UTF-8" standalone="no"?><table-reference xmlns:xt="urn:xpressauthor:trackchanges" graph="None" id="_4712e95f-3c0c-47e2-8a8b-52658d6c3706"><num><xt:insText xt:action="start" xt:author="Jerome Samuel" xt:dateTime="2024-03-18T10:09:00" xt:id="5400691c-d1a8-4b8f-b2e1-efffe76d9ce6"/>B1P1c<xt:insText xt:action="end" xt:id="5400691c-d1a8-4b8f-b2e1-efffe76d9ce6"/></num><title id="_7dc4e2df-3635-4341-aee5-4257df8d034a"><xt:insText xt:action="start" xt:author="Jerome Samuel" xt:dateTime="2024-03-18T10:09:00" xt:id="dc82f412-07cd-4055-819e-c172161d91e1"/>Minimum annual reliability indices (β) for action reversal and stability load combinations (combined gravity and other actions)<xt:insText xt:action="end" xt:id="dc82f412-07cd-4055-819e-c172161d91e1"/></title><table id="_acf4116c-da23-46da-8355-493bca21a0fe" keycol="1" xt:author="Jerome Samuel" xt:dateTime="2024-03-18T10:09:47" xt:type="insert"><tgroup cols="4" xt:author="Jerome Samuel" xt:dateTime="2024-03-18T10:09:47" xt:type="insert"><colspec colname="001" colnum="1" colwidth="108.00*" xt:author="Jerome Samuel" xt:dateTime="2024-03-18T10:09:47" xt:type="insert"/><colspec colname="002" colnum="2" colwidth="108.00*" xt:author="Jerome Samuel" xt:dateTime="2024-03-18T10:09:47" xt:type="insert"/><colspec colname="004" colnum="3" colwidth="108.00*" xt:author="Jerome Samuel" xt:dateTime="2024-03-18T10:09:47" xt:type="insert"/><colspec colname="003" colnum="4" colwidth="108.00*" xt:author="Jerome Samuel" xt:dateTime="2024-03-18T10:09:47" xt:type="insert"/><thead xt:author="Jerome Samuel" xt:dateTime="2024-03-18T10:09:47" xt:type="insert"><row xt:author="Jerome Samuel" xt:dateTime="2024-03-18T10:09:47" xt:type="insert"><entry xt:author="Jerome Samuel" xt:dateTime="2024-03-18T10:09:47" xt:type="insert"><xt:insText xt:action="start" xt:author="Jerome Samuel" xt:dateTime="2024-03-18T10:09:00" xt:id="e67684d6-ad73-4f00-a2e5-619682f997b0"/>Importance Level 1<xt:insText xt:action="end" xt:id="e67684d6-ad73-4f00-a2e5-619682f997b0"/></entry><entry xt:author="Jerome Samuel" xt:dateTime="2024-03-18T10:09:47" xt:type="insert"><xt:insText xt:action="start" xt:author="Jerome Samuel" xt:dateTime="2024-03-18T10:09:00" xt:id="ac52a6b1-6963-4b33-ba3b-85f203ca0c1d"/>Importance Level 2<xt:insText xt:action="end" xt:id="ac52a6b1-6963-4b33-ba3b-85f203ca0c1d"/></entry><entry xt:author="Jerome Samuel" xt:dateTime="2024-03-18T10:09:47" xt:type="insert"><xt:insText xt:action="start" xt:author="Jerome Samuel" xt:dateTime="2024-03-18T10:09:00" xt:id="47af3531-f866-44a5-b60a-62af892f9449"/>Importance Level 3<xt:insText xt:action="end" xt:id="47af3531-f866-44a5-b60a-62af892f9449"/></entry><entry xt:author="Jerome Samuel" xt:dateTime="2024-03-18T10:09:47" xt:type="insert"><xt:insText xt:action="start" xt:author="Jerome Samuel" xt:dateTime="2024-03-18T10:09:00" xt:id="686be6d0-b54d-4927-bb72-60587a68bcac"/>Importance Level 4<xt:insText xt:action="end" xt:id="686be6d0-b54d-4927-bb72-60587a68bcac"/></entry></row></thead><tbody xt:author="Jerome Samuel" xt:dateTime="2024-03-18T10:09:47" xt:type="insert"><row xt:author="Jerome Samuel" xt:dateTime="2024-03-18T10:09:47" xt:type="insert"><entry xt:author="Jerome Samuel" xt:dateTime="2024-03-18T10:09:47" xt:type="insert"><xt:insText xt:action="start" xt:author="Jerome Samuel" xt:dateTime="2024-03-18T10:09:00" xt:id="d90e1ff0-7142-4cad-a59e-460165c4aa30"/>β = 3.00<xt:insText xt:action="end" xt:id="d90e1ff0-7142-4cad-a59e-460165c4aa30"/></entry><entry xt:author="Jerome Samuel" xt:dateTime="2024-03-18T10:09:47" xt:type="insert"><xt:insText xt:action="start" xt:author="Jerome Samuel" xt:dateTime="2024-03-18T10:09:00" xt:id="58342369-d5cf-4476-93aa-6eeed4b4a912"/>β = 3.35<xt:insText xt:action="end" xt:id="58342369-d5cf-4476-93aa-6eeed4b4a912"/></entry><entry xt:author="Jerome Samuel" xt:dateTime="2024-03-18T10:09:47" xt:type="insert"><xt:insText xt:action="start" xt:author="Jerome Samuel" xt:dateTime="2024-03-18T10:09:00" xt:id="64fd59d2-aff6-4369-bd95-b2c7a2bf6051"/>β = 3.55<xt:insText xt:action="end" xt:id="64fd59d2-aff6-4369-bd95-b2c7a2bf6051"/></entry><entry xt:author="Jerome Samuel" xt:dateTime="2024-03-18T10:09:47" xt:type="insert"><xt:insText xt:action="start" xt:author="Jerome Samuel" xt:dateTime="2024-03-18T10:09:00" xt:id="81230819-6912-438f-b01f-2869fe48dfef"/>β = 3.65<xt:insText xt:action="end" xt:id="81230819-6912-438f-b01f-2869fe48dfef"/></entry></row></tbody></tgroup></table><desc-note id="_4e08e86a-e50e-4f6f-aef3-ee3de238a5e5" xt:author="Jerome Samuel" xt:dateTime="2024-03-18T10:13:56" xt:type="insert"><ol outputclass="numbered" xt:author="Jerome Samuel" xt:dateTime="2024-03-18T10:13:59" xt:type="insert"><li id="_cfb7e89b-b43e-4a62-9f14-f552483a9301" xt:author="Jerome Samuel" xt:dateTime="2024-03-18T10:13:59" xt:type="insert"><xt:insText xt:action="start" xt:author="Jerome Samuel" xt:dateTime="2024-03-18T10:14:00" xt:id="794569fc-3fef-4889-8ca4-c807367aef57"/>The annual reliability indices in Table B1P1c must be met for all components necessary to comply with B1P1(1) at the relevant Importance Level.<xt:insText xt:action="end" xt:id="794569fc-3fef-4889-8ca4-c807367aef57"/></li><li id="_d4bc9c17-410c-4f2d-8e79-74c7677097bb" xt:author="Jerome Samuel" xt:dateTime="2024-03-18T10:14:29" xt:type="insert"><xt:insText xt:action="start" xt:author="Jerome Samuel" xt:dateTime="2024-03-18T10:16:00" xt:id="4a6a8867-053d-4283-8f4e-41cadb916c9e"/><xref format="dita" href="/tmp/QppServer/Publishing/5e2c1f63-e589-4ce1-95e8-5c3e286a7aff/9430_0.2.0.xml#_5802c469-ebd4-4cd4-9b70-087839ae099e" id="_cb7bc207-19b5-4835-b25c-d38d26a4ee10" referencetype="Text" scope="local" synctargettext="false" type="abcb-glossentry">Ancillary components</xref> may have a reliability index appropriate to the component, but not less than that <xref format="dita" href="/tmp/QppServer/Publishing/5e2c1f63-e589-4ce1-95e8-5c3e286a7aff/1432_4.0.0.xml#_af6fde9f-147d-4782-8b85-42044e80fd42" id="_2ea47d22-4c42-4ff1-8ff4-6ff5f99a847d" referencetype="Text" scope="local" synctargettext="false" type="abcb-glossentry">required</xref> for Importance Level 1, irrespective of the Importance Level of the whole building or structure.<xt:insText xt:action="end" xt:id="4a6a8867-053d-4283-8f4e-41cadb916c9e"/></li></ol></desc-note></table-reference>